pytheriak/__init__.py
pytheriak/hdfwriter.py
pytheriak/wrapper.py
pytheriak-1.1.1.dist-info/LICENSE
pytheriak-1.1.1.dist-info/METADATA
pytheriak-1.1.1.dist-info/WHEEL
pytheriak-1.1.1.dist-info/RECORD
