Metadata-Version: 2.1
Name: pytheriak
Version: 1.1.1
Summary: Python wrapper functions for Theriak-Domino.
License: GPL-3.0-or-later
Author: Philip Hartmeier
Author-email: philip.hartmeier@hotmail.com
Requires-Python: >=3.10,<4.0
Classifier: Development Status :: 5 - Production/Stable
Classifier: License :: OSI Approved :: GNU General Public License v3 (GPLv3)
Classifier: License :: OSI Approved :: GNU General Public License v3 or later (GPLv3+)
Classifier: Operating System :: OS Independent
Classifier: Programming Language :: Python :: 3
Classifier: Programming Language :: Python :: 3.10
Classifier: Programming Language :: Python :: 3.11
Classifier: Programming Language :: Python :: 3.12
Classifier: Topic :: Scientific/Engineering
Requires-Dist: h5py (>=3.10.0,<4.0.0)
Requires-Dist: numpy (>=1.23,<2.0)
